az/__init__.py
az-0.1.0.dev1.dist-info/METADATA
az-0.1.0.dev1.dist-info/RECORD
az-0.1.0.dev1.dist-info/WHEEL
az-0.1.0.dev1.dist-info/top_level.txt
